MYSMALLSITE/__init__.py
MYSMALLSITE/gener.py
MySmallSite-0.0.1.dist-info/LICENSE
MySmallSite-0.0.1.dist-info/METADATA
MySmallSite-0.0.1.dist-info/WHEEL
MySmallSite-0.0.1.dist-info/top_level.txt
MySmallSite-0.0.1.dist-info/RECORD
